{
  "count": "1",
  "encounter_type": "Individual counselling for Breast Cancer",
  "entity_id": "",
  "relational_id": "",
  "global": {
  },
  "metadata": {
    "start": {
      "openmrs_entity_parent": "",
      "openmrs_entity": "concept",
      "openmrs_data_type": "start",
      "openmrs_entity_id": "165000AAAAAAAAAAAAAAAAAAAAAAAAAAAAAA"
    },
    "end": {
      "openmrs_entity_parent": "",
      "openmrs_entity": "concept",
      "openmrs_data_type": "end",
      "openmrs_entity_id": "165001AAAAAAAAAAAAAAAAAAAAAAAAAAAAAA"
    },
    "today": {
      "openmrs_entity_parent": "",
      "openmrs_entity": "encounter",
      "openmrs_entity_id": "encounter_date"
    },
    "deviceid": {
      "openmrs_entity_parent": "",
      "openmrs_entity": "concept",
      "openmrs_data_type": "deviceid",
      "openmrs_entity_id": "165003AAAAAAAAAAAAAAAAAAAAAAAAAAAAAA"
    },
    "subscriberid": {
      "openmrs_entity_parent": "",
      "openmrs_entity": "concept",
      "openmrs_data_type": "subscriberid",
      "openmrs_entity_id": "165004AAAAAAAAAAAAAAAAAAAAAAAAAAAAAA"
    },
    "simserial": {
      "openmrs_entity_parent": "",
      "openmrs_entity": "concept",
      "openmrs_data_type": "simserial",
      "openmrs_entity_id": "165005AAAAAAAAAAAAAAAAAAAAAAAAAAAAAA"
    },
    "phonenumber": {
      "openmrs_entity_parent": "",
      "openmrs_entity": "concept",
      "openmrs_data_type": "phonenumber",
      "openmrs_entity_id": "165006AAAAAAAAAAAAAAAAAAAAAAAAAAAAAA"
    },
    "encounter_location": "",
    "look_up": {
      "entity_id": "",
      "value": ""
    }
  },
  "step1": {
    "title": "Individual counselling for Breast Cancer",
    "fields": [
      {
        "key": "abnormal_breast_concern",
        "openmrs_entity_parent": "",
        "openmrs_entity": "concept",
        "openmrs_entity_id": "abnormal_breast_concern",
        "type": "native_radio",
        "label": "Any abnormal breast concern?",
        "text_color": "#000000",
        "options": [
          {
            "key": "yes",
            "text": "Yes",
            "openmrs_entity": "concept",
            "openmrs_entity_id": "yes"
          },
          {
            "key": "no",
            "text": "No",
            "openmrs_entity": "concept",
            "openmrs_entity_id": "no"
          }
        ]
      },
      {
        "key": "family_history_breast_cancer",
        "openmrs_entity_parent": "",
        "openmrs_entity": "concept",
        "openmrs_entity_id": "family_history_breast_cancer",
        "type": "native_radio",
        "label": "Is there family history of Breast Cancer?",
        "text_color": "#000000",
        "options": [
          {
            "key": "yes",
            "text": "Yes",
            "openmrs_entity": "concept",
            "openmrs_entity_id": "yes"
          },
          {
            "key": "no",
            "text": "No",
            "openmrs_entity": "concept",
            "openmrs_entity_id": "no"
          }
        ],
        "relevance": {
          "rules-engine": {
            "ex-rules": {
              "rules-file": "cecap_individual_counseling_for_breast_cancer_rule.yml"
            }
          }
        }
      },
      {
        "key": "prompt_for_mammograph",
        "type": "toaster_notes",
        "text": "Recommend for Mammograph",
        "openmrs_entity_id": "prompt_for_mammograph",
        "openmrs_entity": "concept",
        "openmrs_entity_parent": "",
        "toaster_type": "problem",
        "relevance": {
          "rules-engine": {
            "ex-rules": {
              "rules-file": "cecap_individual_counseling_for_breast_cancer_rule.yml"
            }
          }
        }
      },
      {
        "key": "eligible_for_breast_cancer_screening",
        "openmrs_entity_parent": "",
        "openmrs_entity": "concept",
        "openmrs_entity_id": "eligible_for_breast_cancer_screening",
        "type": "hidden",
        "calculation": {
          "rules-engine": {
            "ex-rules": {
              "rules-file": "cecap_individual_counseling_for_breast_cancer_rule.yml"
            }
          }
        }
      }
    ]
  }
}
